{"_class":"document","do_objectID":"21d33c01-a251-4ee1-a708-984e7b7e27ae","assets":{"_class":"assetCollection","colors":[]},"currentPageIndex":0,"enableLayerInteraction":true,"enableSliceInteraction":true,"foreignSymbols":[],"layerStyles":{"_class":"sharedStyleContainer","objects":[]},"layerSymbols":{"_class":"symbolContainer","objects":[]},"layerTextStyles":{"_class":"sharedTextStyleContainer","objects":[{"_class":"sharedStyle","do_objectID":"27f3d245-f449-4dca-a0ce-68b7ee085668","name":"elements/links/links-invert","style":{"color":"rgb(255, 255, 255)","fontSize":22,"fontFamily":"Noto Sans","fontWeight":400,"lineHeight":30,"textDecoration":"underline","textAlign":"start","textTransform":"none"}},{"_class":"sharedStyle","do_objectID":"bf9f5c48-984f-4d65-917c-9ceac830b8e3","name":"elements/links/links","style":{"color":"rgb(24, 78, 158)","fontSize":22,"fontFamily":"Noto Sans","fontWeight":400,"lineHeight":30,"textDecoration":"underline","textAlign":"start","textTransform":"none"}},{"_class":"sharedStyle","do_objectID":"e198edf8-1fff-4a10-a30c-ffb7e62de39b","name":"elements/typography/type-blockquote","style":{"color":"rgb(0, 0, 0)","fontSize":22,"fontFamily":"Noto Serif","fontWeight":400,"lineHeight":28,"textDecoration":"none","textAlign":"start","textTransform":"none"}},{"_class":"sharedStyle","do_objectID":"ff174a1f-60b5-48d4-b2ee-627a61211cf8","name":"elements/typography/type-exposition","style":{"color":"rgb(0, 0, 0)","fontSize":31,"fontFamily":"Noto Serif","fontWeight":400,"lineHeight":41,"textDecoration":"none","textAlign":"start","textTransform":"none"}},{"_class":"sharedStyle","do_objectID":"8576fb83-6f60-4657-95e5-699bc59ac0e4","name":"elements/typography/type-headings","style":{"color":"rgb(0, 0, 0)","fontSize":39,"fontFamily":"Noto Serif","fontWeight":400,"lineHeight":51,"textDecoration":"none","textAlign":"start","textTransform":"none"}},{"_class":"sharedStyle","do_objectID":"5ef9095f-fa2a-4e5b-bbf8-9a149f0fbd09","name":"elements/typography/type-headings","style":{"color":"rgb(0, 0, 0)","fontSize":31,"fontFamily":"Noto Serif","fontWeight":700,"lineHeight":41,"textDecoration":"none","textAlign":"start","textTransform":"none"}},{"_class":"sharedStyle","do_objectID":"0d4e5a8d-cc07-4b4c-bced-89852ba0e646","name":"elements/typography/type-headings","style":{"color":"rgb(0, 0, 0)","fontSize":27,"fontFamily":"Noto Serif","fontWeight":700,"lineHeight":35,"textDecoration":"none","textAlign":"start","textTransform":"none"}},{"_class":"sharedStyle","do_objectID":"bf262949-66e8-4f64-b718-f85df97a647c","name":"elements/typography/type-headings","style":{"color":"rgb(0, 0, 0)","fontSize":23,"fontFamily":"Noto Sans","fontWeight":700,"lineHeight":31,"textDecoration":"none","textAlign":"start","textTransform":"none"}},{"_class":"sharedStyle","do_objectID":"f57183a5-d62d-46f2-8ded-11ea0992f6f6","name":"elements/typography/type-headings","style":{"color":"rgb(0, 0, 0)","fontSize":22,"fontFamily":"Noto Sans","fontWeight":400,"lineHeight":28,"textDecoration":"none","textAlign":"start","textTransform":"none"}},{"_class":"sharedStyle","do_objectID":"29c04e96-b367-4354-ae52-2ad757601dc8","name":"elements/typography/type-jumbo","style":{"color":"rgb(0, 0, 0)","fontSize":55,"fontFamily":"Noto Serif","fontWeight":400,"lineHeight":72,"textDecoration":"none","textAlign":"start","textTransform":"none"}},{"_class":"sharedStyle","do_objectID":"1d9bb9ec-f6ee-41ec-9b28-5f74977e9a0b","name":"elements/typography/type-supplemental","style":{"color":"rgb(0, 0, 0)","fontSize":22,"fontFamily":"Noto Sans","fontWeight":400,"lineHeight":28,"textDecoration":"none","textAlign":"start","textTransform":"none"}}]},"pages":[]}